{
 "actions": [],
 "allow_rename": 1,
 "creation": "2022-04-15 13:28:35.864934",
 "doctype": "DocType",
 "editable_grid": 1,
 "engine": "InnoDB",
 "field_order": [
  "item",
  "work",
  "compound_wall_type",
  "height",
  "pcs",
  "double_post",
  "running_sqft",
  "allocated_ft",
  "rate",
  "amount",
  "sales_order"
 ],
 "fields": [
  {
   "columns": 1,
   "fieldname": "item",
   "fieldtype": "Link",
   "in_list_view": 1,
   "label": "Item",
   "options": "Item",
   "reqd": 1,
   "width": "2"
  },
  {
   "columns": 1,
   "fieldname": "compound_wall_type",
   "fieldtype": "Select",
   "in_list_view": 1,
   "label": "Compound Wall Type",
   "options": "\nSlab\nPost",
   "reqd": 1,
   "width": "1"
  },
  {
   "fieldname": "sales_order",
   "fieldtype": "Link",
   "label": "Sales Order",
   "options": "Sales Order"
  },
  {
   "columns": 1,
   "fieldname": "height",
   "fieldtype": "Float",
   "in_list_view": 1,
   "label": "Height",
   "width": "1"
  },
  {
   "columns": 1,
   "fieldname": "pcs",
   "fieldtype": "Int",
   "in_list_view": 1,
   "label": "Pcs",
   "width": "1"
  },
  {
   "columns": 1,
   "fieldname": "double_post",
   "fieldtype": "Int",
   "in_list_view": 1,
   "label": "Double Post",
   "width": "1"
  },
  {
   "columns": 1,
   "fieldname": "running_sqft",
   "fieldtype": "Float",
   "in_list_view": 1,
   "label": "Running Sqft",
   "width": "1"
  },
  {
   "columns": 1,
   "fieldname": "allocated_ft",
   "fieldtype": "Float",
   "in_list_view": 1,
   "label": "Allocated ft",
   "width": "1"
  },
  {
   "columns": 1,
   "fieldname": "rate",
   "fieldtype": "Currency",
   "in_list_view": 1,
   "label": "Rate",
   "width": "1"
  },
  {
   "columns": 1,
   "fieldname": "amount",
   "fieldtype": "Currency",
   "in_list_view": 1,
   "label": "Amount",
   "width": "1"
  },
  {
   "fieldname": "work",
   "fieldtype": "Select",
   "in_list_view": 1,
   "label": "Work",
   "options": "\nSupply Only\nLaying Only\nSupply & Laying",
   "reqd": 1
  }
 ],
 "index_web_pages_for_search": 1,
 "istable": 1,
 "links": [],
 "modified": "2022-04-19 11:12:07.710969",
 "modified_by": "Administrator",
 "module": "Ganapathy Pavers",
 "name": "Compound Wall",
 "owner": "Administrator",
 "permissions": [],
 "sort_field": "modified",
 "sort_order": "DESC"
}