{
 "custom_fields": [],
 "custom_perms": [],
 "doctype": "CW Items",
 "property_setters": [
  {
   "_assign": null,
   "_comments": null,
   "_liked_by": null,
   "_user_tags": null,
   "creation": "2022-10-07 12:16:57.345805",
   "default_value": null,
   "doc_type": "CW Items",
   "docstatus": 0,
   "doctype_or_field": "DocField",
   "field_name": "produced_qty",
   "idx": 0,
   "modified": "2022-10-07 12:16:57.345805",
   "modified_by": "Administrator",
   "name": "CW Items-produced_qty-precision",
   "owner": "Administrator",
   "parent": null,
   "parentfield": null,
   "parenttype": null,
   "property": "precision",
   "property_type": "Select",
   "row_name": null,
   "value": "4"
  },
  {
   "_assign": null,
   "_comments": null,
   "_liked_by": null,
   "_user_tags": null,
   "creation": "2022-10-07 12:16:57.295607",
   "default_value": null,
   "doc_type": "CW Items",
   "docstatus": 0,
   "doctype_or_field": "DocField",
   "field_name": "damaged_qty",
   "idx": 0,
   "modified": "2022-10-07 12:16:57.295607",
   "modified_by": "Administrator",
   "name": "CW Items-damaged_qty-precision",
   "owner": "Administrator",
   "parent": null,
   "parentfield": null,
   "parenttype": null,
   "property": "precision",
   "property_type": "Select",
   "row_name": null,
   "value": "4"
  },
  {
   "_assign": null,
   "_comments": null,
   "_liked_by": null,
   "_user_tags": null,
   "creation": "2022-10-07 12:16:57.217552",
   "default_value": null,
   "doc_type": "CW Items",
   "docstatus": 0,
   "doctype_or_field": "DocField",
   "field_name": "production_qty",
   "idx": 0,
   "modified": "2022-10-07 12:16:57.217552",
   "modified_by": "Administrator",
   "name": "CW Items-production_qty-precision",
   "owner": "Administrator",
   "parent": null,
   "parentfield": null,
   "parenttype": null,
   "property": "precision",
   "property_type": "Select",
   "row_name": null,
   "value": "4"
  }
 ],
 "sync_on_migrate": 1
}