{
 "custom_fields": [
  {
   "_assign": null,
   "_comments": null,
   "_liked_by": null,
   "_user_tags": null,
   "allow_in_quick_entry": 0,
   "allow_on_submit": 0,
   "bold": 0,
   "collapsible": 0,
   "collapsible_depends_on": null,
   "columns": 0,
   "creation": "2021-12-16 12:50:28.806076",
   "default": null,
   "depends_on": null,
   "description": null,
   "docstatus": 0,
   "dt": "Sales Order",
   "fetch_from": "customer_address.gstin",
   "fetch_if_empty": 0,
   "fieldname": "billing_address_gstin",
   "fieldtype": "Data",
   "hidden": 0,
   "hide_border": 0,
   "hide_days": 0,
   "hide_seconds": 0,
   "idx": 21,
   "ignore_user_permissions": 0,
   "ignore_xss_filter": 0,
   "in_global_search": 0,
   "in_list_view": 0,
   "in_preview": 0,
   "in_standard_filter": 0,
   "insert_after": "customer_address",
   "label": "Billing Address GSTIN",
   "length": 15,
   "mandatory_depends_on": null,
   "modified": "2021-12-16 12:50:28.806076",
   "modified_by": "Administrator",
   "name": "Sales Order-billing_address_gstin",
   "no_copy": 0,
   "non_negative": 0,
   "options": null,
   "owner": "Administrator",
   "parent": null,
   "parentfield": null,
   "parenttype": null,
   "permlevel": 0,
   "precision": "",
   "print_hide": 1,
   "print_hide_if_no_value": 0,
   "print_width": null,
   "read_only": 1,
   "read_only_depends_on": null,
   "report_hide": 0,
   "reqd": 0,
   "search_index": 0,
   "translatable": 1,
   "unique": 0,
   "width": null
  },
  {
   "_assign": null,
   "_comments": null,
   "_liked_by": null,
   "_user_tags": null,
   "allow_in_quick_entry": 0,
   "allow_on_submit": 0,
   "bold": 0,
   "collapsible": 0,
   "collapsible_depends_on": null,
   "columns": 0,
   "creation": "2021-12-16 12:50:28.880909",
   "default": null,
   "depends_on": null,
   "description": null,
   "docstatus": 0,
   "dt": "Sales Order",
   "fetch_from": "shipping_address_name.gstin",
   "fetch_if_empty": 0,
   "fieldname": "customer_gstin",
   "fieldtype": "Data",
   "hidden": 0,
   "hide_border": 0,
   "hide_days": 0,
   "hide_seconds": 0,
   "idx": 33,
   "ignore_user_permissions": 0,
   "ignore_xss_filter": 0,
   "in_global_search": 0,
   "in_list_view": 0,
   "in_preview": 0,
   "in_standard_filter": 0,
   "insert_after": "shipping_address_name",
   "label": "Customer GSTIN",
   "length": 15,
   "mandatory_depends_on": null,
   "modified": "2021-12-16 12:50:28.880909",
   "modified_by": "Administrator",
   "name": "Sales Order-customer_gstin",
   "no_copy": 0,
   "non_negative": 0,
   "options": null,
   "owner": "Administrator",
   "parent": null,
   "parentfield": null,
   "parenttype": null,
   "permlevel": 0,
   "precision": "",
   "print_hide": 1,
   "print_hide_if_no_value": 0,
   "print_width": null,
   "read_only": 0,
   "read_only_depends_on": null,
   "report_hide": 0,
   "reqd": 0,
   "search_index": 0,
   "translatable": 1,
   "unique": 0,
   "width": null
  },
  {
   "_assign": null,
   "_comments": null,
   "_liked_by": null,
   "_user_tags": null,
   "allow_in_quick_entry": 0,
   "allow_on_submit": 0,
   "bold": 0,
   "collapsible": 0,
   "collapsible_depends_on": null,
   "columns": 0,
   "creation": "2021-12-16 12:50:28.955012",
   "default": null,
   "depends_on": null,
   "description": null,
   "docstatus": 0,
   "dt": "Sales Order",
   "fetch_from": null,
   "fetch_if_empty": 0,
   "fieldname": "place_of_supply",
   "fieldtype": "Data",
   "hidden": 0,
   "hide_border": 0,
   "hide_days": 0,
   "hide_seconds": 0,
   "idx": 34,
   "ignore_user_permissions": 0,
   "ignore_xss_filter": 0,
   "in_global_search": 0,
   "in_list_view": 0,
   "in_preview": 0,
   "in_standard_filter": 0,
   "insert_after": "customer_gstin",
   "label": "Place of Supply",
   "length": 50,
   "mandatory_depends_on": null,
   "modified": "2021-12-16 12:50:28.955012",
   "modified_by": "Administrator",
   "name": "Sales Order-place_of_supply",
   "no_copy": 0,
   "non_negative": 0,
   "options": null,
   "owner": "Administrator",
   "parent": null,
   "parentfield": null,
   "parenttype": null,
   "permlevel": 0,
   "precision": "",
   "print_hide": 1,
   "print_hide_if_no_value": 0,
   "print_width": null,
   "read_only": 1,
   "read_only_depends_on": null,
   "report_hide": 0,
   "reqd": 0,
   "search_index": 0,
   "translatable": 1,
   "unique": 0,
   "width": null
  },
  {
   "_assign": null,
   "_comments": null,
   "_liked_by": null,
   "_user_tags": null,
   "allow_in_quick_entry": 0,
   "allow_on_submit": 0,
   "bold": 0,
   "collapsible": 0,
   "collapsible_depends_on": null,
   "columns": 0,
   "creation": "2021-12-16 12:50:29.028752",
   "default": null,
   "depends_on": null,
   "description": null,
   "docstatus": 0,
   "dt": "Sales Order",
   "fetch_from": "company_address.gstin",
   "fetch_if_empty": 0,
   "fieldname": "company_gstin",
   "fieldtype": "Data",
   "hidden": 0,
   "hide_border": 0,
   "hide_days": 0,
   "hide_seconds": 0,
   "idx": 29,
   "ignore_user_permissions": 0,
   "ignore_xss_filter": 0,
   "in_global_search": 0,
   "in_list_view": 0,
   "in_preview": 0,
   "in_standard_filter": 0,
   "insert_after": "company_address",
   "label": "Company GSTIN",
   "length": 15,
   "mandatory_depends_on": null,
   "modified": "2021-12-16 12:50:29.028752",
   "modified_by": "Administrator",
   "name": "Sales Order-company_gstin",
   "no_copy": 0,
   "non_negative": 0,
   "options": null,
   "owner": "Administrator",
   "parent": null,
   "parentfield": null,
   "parenttype": null,
   "permlevel": 0,
   "precision": "",
   "print_hide": 1,
   "print_hide_if_no_value": 0,
   "print_width": null,
   "read_only": 1,
   "read_only_depends_on": null,
   "report_hide": 0,
   "reqd": 0,
   "search_index": 0,
   "translatable": 1,
   "unique": 0,
   "width": null
  },
  {
   "_assign": null,
   "_comments": null,
   "_liked_by": null,
   "_user_tags": null,
   "allow_in_quick_entry": 0,
   "allow_on_submit": 0,
   "bold": 0,
   "collapsible": 0,
   "collapsible_depends_on": "",
   "columns": 0,
   "creation": "2022-04-07 15:48:40.220505",
   "default": null,
   "depends_on": "eval:doc.type=='Pavers'",
   "description": null,
   "docstatus": 0,
   "dt": "Sales Order",
   "fetch_from": null,
   "fetch_if_empty": 0,
   "fieldname": "pavers",
   "fieldtype": "Table",
   "hidden": 0,
   "hide_border": 0,
   "hide_days": 0,
   "hide_seconds": 0,
   "idx": 53,
   "ignore_user_permissions": 0,
   "ignore_xss_filter": 0,
   "in_global_search": 0,
   "in_list_view": 0,
   "in_preview": 0,
   "in_standard_filter": 0,
   "insert_after": "items",
   "label": "Pavers",
   "length": 0,
   "mandatory_depends_on": null,
   "modified": "2022-04-07 15:48:40.220505",
   "modified_by": "Administrator",
   "name": "Sales Order-pavers",
   "no_copy": 0,
   "non_negative": 0,
   "options": "Item Detail Pavers",
   "owner": "Administrator",
   "parent": null,
   "parentfield": null,
   "parenttype": null,
   "permlevel": 0,
   "precision": "",
   "print_hide": 0,
   "print_hide_if_no_value": 0,
   "print_width": null,
   "read_only": 0,
   "read_only_depends_on": null,
   "report_hide": 0,
   "reqd": 0,
   "search_index": 0,
   "translatable": 0,
   "unique": 0,
   "width": null
  },
  {
   "_assign": null,
   "_comments": null,
   "_liked_by": null,
   "_user_tags": null,
   "allow_in_quick_entry": 0,
   "allow_on_submit": 0,
   "bold": 0,
   "collapsible": 0,
   "collapsible_depends_on": null,
   "columns": 0,
   "creation": "2022-04-07 15:49:25.104756",
   "default": null,
   "depends_on": "eval:doc.type=='Compound Wall'",
   "description": null,
   "docstatus": 0,
   "dt": "Sales Order",
   "fetch_from": null,
   "fetch_if_empty": 0,
   "fieldname": "compoun_walls",
   "fieldtype": "Table",
   "hidden": 0,
   "hide_border": 0,
   "hide_days": 0,
   "hide_seconds": 0,
   "idx": 54,
   "ignore_user_permissions": 0,
   "ignore_xss_filter": 0,
   "in_global_search": 0,
   "in_list_view": 0,
   "in_preview": 0,
   "in_standard_filter": 0,
   "insert_after": "pavers",
   "label": "Compoun Walls",
   "length": 0,
   "mandatory_depends_on": null,
   "modified": "2022-04-07 15:49:25.104756",
   "modified_by": "Administrator",
   "name": "Sales Order-compoun_walls",
   "no_copy": 0,
   "non_negative": 0,
   "options": "Item Detail Compound Wall",
   "owner": "Administrator",
   "parent": null,
   "parentfield": null,
   "parenttype": null,
   "permlevel": 0,
   "precision": "",
   "print_hide": 0,
   "print_hide_if_no_value": 0,
   "print_width": null,
   "read_only": 0,
   "read_only_depends_on": null,
   "report_hide": 0,
   "reqd": 0,
   "search_index": 0,
   "translatable": 0,
   "unique": 0,
   "width": null
  },
  {
   "_assign": null,
   "_comments": null,
   "_liked_by": null,
   "_user_tags": null,
   "allow_in_quick_entry": 0,
   "allow_on_submit": 0,
   "bold": 0,
   "collapsible": 0,
   "collapsible_depends_on": null,
   "columns": 0,
   "creation": "2022-04-07 16:28:45.507006",
   "default": null,
   "depends_on": null,
   "description": null,
   "docstatus": 0,
   "dt": "Sales Order",
   "fetch_from": null,
   "fetch_if_empty": 0,
   "fieldname": "type",
   "fieldtype": "Select",
   "hidden": 0,
   "hide_border": 0,
   "hide_days": 0,
   "hide_seconds": 0,
   "idx": 6,
   "ignore_user_permissions": 0,
   "ignore_xss_filter": 0,
   "in_global_search": 0,
   "in_list_view": 0,
   "in_preview": 0,
   "in_standard_filter": 0,
   "insert_after": "customer",
   "label": "Type",
   "length": 0,
   "mandatory_depends_on": null,
   "modified": "2022-04-07 16:28:45.507006",
   "modified_by": "Administrator",
   "name": "Sales Order-type",
   "no_copy": 0,
   "non_negative": 0,
   "options": "\nPavers\nCompound Wall",
   "owner": "Administrator",
   "parent": null,
   "parentfield": null,
   "parenttype": null,
   "permlevel": 0,
   "precision": "",
   "print_hide": 0,
   "print_hide_if_no_value": 0,
   "print_width": null,
   "read_only": 0,
   "read_only_depends_on": null,
   "report_hide": 0,
   "reqd": 1,
   "search_index": 0,
   "translatable": 1,
   "unique": 0,
   "width": null
  },
  {
   "_assign": null,
   "_comments": null,
   "_liked_by": null,
   "_user_tags": null,
   "allow_in_quick_entry": 0,
   "allow_on_submit": 0,
   "bold": 0,
   "collapsible": 0,
   "collapsible_depends_on": null,
   "columns": 0,
   "creation": "2022-04-11 12:48:55.987424",
   "default": null,
   "depends_on": null,
   "description": null,
   "docstatus": 0,
   "dt": "Sales Order",
   "fetch_from": null,
   "fetch_if_empty": 0,
   "fieldname": "site_work",
   "fieldtype": "Data",
   "hidden": 0,
   "hide_border": 0,
   "hide_days": 0,
   "hide_seconds": 0,
   "idx": 7,
   "ignore_user_permissions": 0,
   "ignore_xss_filter": 0,
   "in_global_search": 0,
   "in_list_view": 0,
   "in_preview": 0,
   "in_standard_filter": 0,
   "insert_after": "type",
   "label": "Site Work",
   "length": 0,
   "mandatory_depends_on": null,
   "modified": "2022-04-11 12:48:55.987424",
   "modified_by": "Administrator",
   "name": "Sales Order-site_work",
   "no_copy": 0,
   "non_negative": 0,
   "options": null,
   "owner": "Administrator",
   "parent": null,
   "parentfield": null,
   "parenttype": null,
   "permlevel": 0,
   "precision": "",
   "print_hide": 0,
   "print_hide_if_no_value": 0,
   "print_width": null,
   "read_only": 0,
   "read_only_depends_on": null,
   "report_hide": 0,
   "reqd": 1,
   "search_index": 0,
   "translatable": 1,
   "unique": 0,
   "width": null
  }
 ],
 "custom_perms": [],
 "doctype": "Sales Order",
 "property_setters": [
  {
   "_assign": null,
   "_comments": null,
   "_liked_by": null,
   "_user_tags": null,
   "creation": "2022-04-12 09:51:07.684540",
   "default_value": null,
   "doc_type": "Sales Order",
   "docstatus": 0,
   "doctype_or_field": "DocField",
   "field_name": "more_info",
   "idx": 0,
   "modified": "2022-04-12 09:51:07.684540",
   "modified_by": "Administrator",
   "name": "Sales Order-more_info-hidden",
   "owner": "Administrator",
   "parent": null,
   "parentfield": null,
   "parenttype": null,
   "property": "hidden",
   "property_type": "Check",
   "row_name": null,
   "value": "1"
  },
  {
   "_assign": null,
   "_comments": null,
   "_liked_by": null,
   "_user_tags": null,
   "creation": "2022-04-12 09:50:44.789986",
   "default_value": null,
   "doc_type": "Sales Order",
   "docstatus": 0,
   "doctype_or_field": "DocField",
   "field_name": "set_warehouse",
   "idx": 0,
   "modified": "2022-04-12 09:50:44.789986",
   "modified_by": "Administrator",
   "name": "Sales Order-set_warehouse-hidden",
   "owner": "Administrator",
   "parent": null,
   "parentfield": null,
   "parenttype": null,
   "property": "hidden",
   "property_type": "Check",
   "row_name": null,
   "value": "1"
  },
  {
   "_assign": null,
   "_comments": null,
   "_liked_by": null,
   "_user_tags": null,
   "creation": "2022-04-11 17:04:06.173435",
   "default_value": null,
   "doc_type": "Sales Order",
   "docstatus": 0,
   "doctype_or_field": "DocField",
   "field_name": "section_break1",
   "idx": 0,
   "modified": "2022-04-11 17:04:06.173435",
   "modified_by": "Administrator",
   "name": "Sales Order-section_break1-hidden",
   "owner": "Administrator",
   "parent": null,
   "parentfield": null,
   "parenttype": null,
   "property": "hidden",
   "property_type": "Check",
   "row_name": null,
   "value": "1"
  },
  {
   "_assign": null,
   "_comments": null,
   "_liked_by": null,
   "_user_tags": null,
   "creation": "2022-04-11 17:04:05.862980",
   "default_value": null,
   "doc_type": "Sales Order",
   "docstatus": 0,
   "doctype_or_field": "DocField",
   "field_name": "sales_team_section_break",
   "idx": 0,
   "modified": "2022-04-11 17:04:05.862980",
   "modified_by": "Administrator",
   "name": "Sales Order-sales_team_section_break-hidden",
   "owner": "Administrator",
   "parent": null,
   "parentfield": null,
   "parenttype": null,
   "property": "hidden",
   "property_type": "Check",
   "row_name": null,
   "value": "1"
  },
  {
   "_assign": null,
   "_comments": null,
   "_liked_by": null,
   "_user_tags": null,
   "creation": "2022-04-11 17:03:46.669409",
   "default_value": null,
   "doc_type": "Sales Order",
   "docstatus": 0,
   "doctype_or_field": "DocField",
   "field_name": "section_break_48",
   "idx": 0,
   "modified": "2022-04-11 17:03:46.669409",
   "modified_by": "Administrator",
   "name": "Sales Order-section_break_48-hidden",
   "owner": "Administrator",
   "parent": null,
   "parentfield": null,
   "parenttype": null,
   "property": "hidden",
   "property_type": "Check",
   "row_name": null,
   "value": "1"
  },
  {
   "_assign": null,
   "_comments": null,
   "_liked_by": null,
   "_user_tags": null,
   "creation": "2022-04-11 17:03:02.229695",
   "default_value": null,
   "doc_type": "Sales Order",
   "docstatus": 0,
   "doctype_or_field": "DocField",
   "field_name": "po_date",
   "idx": 0,
   "modified": "2022-04-11 17:03:02.229695",
   "modified_by": "Administrator",
   "name": "Sales Order-po_date-hidden",
   "owner": "Administrator",
   "parent": null,
   "parentfield": null,
   "parenttype": null,
   "property": "hidden",
   "property_type": "Check",
   "row_name": null,
   "value": "1"
  },
  {
   "_assign": null,
   "_comments": null,
   "_liked_by": null,
   "_user_tags": null,
   "creation": "2022-04-11 17:03:01.826646",
   "default_value": null,
   "doc_type": "Sales Order",
   "docstatus": 0,
   "doctype_or_field": "DocField",
   "field_name": "po_no",
   "idx": 0,
   "modified": "2022-04-11 17:03:01.826646",
   "modified_by": "Administrator",
   "name": "Sales Order-po_no-hidden",
   "owner": "Administrator",
   "parent": null,
   "parentfield": null,
   "parenttype": null,
   "property": "hidden",
   "property_type": "Check",
   "row_name": null,
   "value": "1"
  },
  {
   "_assign": null,
   "_comments": null,
   "_liked_by": null,
   "_user_tags": null,
   "creation": "2022-03-26 11:19:48.527019",
   "default_value": null,
   "doc_type": "Sales Order",
   "docstatus": 0,
   "doctype_or_field": "DocField",
   "field_name": "naming_series",
   "idx": 0,
   "modified": "2022-03-26 11:19:48.527019",
   "modified_by": "Administrator",
   "name": "Sales Order-naming_series-default",
   "owner": "Administrator",
   "parent": null,
   "parentfield": null,
   "parenttype": null,
   "property": "default",
   "property_type": "Text",
   "row_name": null,
   "value": "SGP-SO-.MM.YY.-"
  },
  {
   "_assign": null,
   "_comments": null,
   "_liked_by": null,
   "_user_tags": null,
   "creation": "2022-03-14 14:03:34.261902",
   "default_value": null,
   "doc_type": "Sales Order",
   "docstatus": 0,
   "doctype_or_field": "DocField",
   "field_name": "naming_series",
   "idx": 0,
   "modified": "2022-03-26 11:19:48.456101",
   "modified_by": "Administrator",
   "name": "Sales Order-naming_series-options",
   "owner": "Administrator",
   "parent": null,
   "parentfield": null,
   "parenttype": null,
   "property": "options",
   "property_type": "Text",
   "row_name": null,
   "value": "SGP-SO-.MM.YY.-"
  },
  {
   "_assign": null,
   "_comments": null,
   "_liked_by": null,
   "_user_tags": null,
   "creation": "2022-03-14 14:03:07.553843",
   "default_value": null,
   "doc_type": "Sales Order",
   "docstatus": 0,
   "doctype_or_field": "DocField",
   "field_name": "tc_name",
   "idx": 0,
   "modified": "2022-03-14 14:03:07.553843",
   "modified_by": "Administrator",
   "name": "Sales Order-tc_name-default",
   "owner": "Administrator",
   "parent": null,
   "parentfield": null,
   "parenttype": null,
   "property": "default",
   "property_type": "Text",
   "row_name": null,
   "value": ""
  },
  {
   "_assign": null,
   "_comments": null,
   "_liked_by": null,
   "_user_tags": null,
   "creation": "2022-03-14 13:58:03.946807",
   "default_value": null,
   "doc_type": "Sales Order",
   "docstatus": 0,
   "doctype_or_field": "DocField",
   "field_name": "subscription_section",
   "idx": 0,
   "modified": "2022-03-14 13:58:03.946807",
   "modified_by": "Administrator",
   "name": "Sales Order-subscription_section-collapsible",
   "owner": "Administrator",
   "parent": null,
   "parentfield": null,
   "parenttype": null,
   "property": "collapsible",
   "property_type": "Check",
   "row_name": null,
   "value": "0"
  },
  {
   "_assign": null,
   "_comments": null,
   "_liked_by": null,
   "_user_tags": null,
   "creation": "2022-03-14 13:58:03.822474",
   "default_value": null,
   "doc_type": "Sales Order",
   "docstatus": 0,
   "doctype_or_field": "DocField",
   "field_name": "sales_team_section_break",
   "idx": 0,
   "modified": "2022-03-14 13:58:03.822474",
   "modified_by": "Administrator",
   "name": "Sales Order-sales_team_section_break-collapsible",
   "owner": "Administrator",
   "parent": null,
   "parentfield": null,
   "parenttype": null,
   "property": "collapsible",
   "property_type": "Check",
   "row_name": null,
   "value": "0"
  },
  {
   "_assign": null,
   "_comments": null,
   "_liked_by": null,
   "_user_tags": null,
   "creation": "2022-03-14 13:58:03.703005",
   "default_value": null,
   "doc_type": "Sales Order",
   "docstatus": 0,
   "doctype_or_field": "DocField",
   "field_name": "section_break_78",
   "idx": 0,
   "modified": "2022-03-14 13:58:03.703005",
   "modified_by": "Administrator",
   "name": "Sales Order-section_break_78-collapsible",
   "owner": "Administrator",
   "parent": null,
   "parentfield": null,
   "parenttype": null,
   "property": "collapsible",
   "property_type": "Check",
   "row_name": null,
   "value": "0"
  },
  {
   "_assign": null,
   "_comments": null,
   "_liked_by": null,
   "_user_tags": null,
   "creation": "2022-03-14 13:58:03.585638",
   "default_value": null,
   "doc_type": "Sales Order",
   "docstatus": 0,
   "doctype_or_field": "DocField",
   "field_name": "printing_details",
   "idx": 0,
   "modified": "2022-03-14 13:58:03.585638",
   "modified_by": "Administrator",
   "name": "Sales Order-printing_details-collapsible",
   "owner": "Administrator",
   "parent": null,
   "parentfield": null,
   "parenttype": null,
   "property": "collapsible",
   "property_type": "Check",
   "row_name": null,
   "value": "0"
  },
  {
   "_assign": null,
   "_comments": null,
   "_liked_by": null,
   "_user_tags": null,
   "creation": "2022-03-14 13:58:03.459615",
   "default_value": null,
   "doc_type": "Sales Order",
   "docstatus": 0,
   "doctype_or_field": "DocField",
   "field_name": "terms_section_break",
   "idx": 0,
   "modified": "2022-03-14 13:58:03.459615",
   "modified_by": "Administrator",
   "name": "Sales Order-terms_section_break-collapsible",
   "owner": "Administrator",
   "parent": null,
   "parentfield": null,
   "parenttype": null,
   "property": "collapsible",
   "property_type": "Check",
   "row_name": null,
   "value": "0"
  },
  {
   "_assign": null,
   "_comments": null,
   "_liked_by": null,
   "_user_tags": null,
   "creation": "2022-03-14 13:58:03.324738",
   "default_value": null,
   "doc_type": "Sales Order",
   "docstatus": 0,
   "doctype_or_field": "DocField",
   "field_name": "section_break_48",
   "idx": 0,
   "modified": "2022-03-14 13:58:03.324738",
   "modified_by": "Administrator",
   "name": "Sales Order-section_break_48-collapsible",
   "owner": "Administrator",
   "parent": null,
   "parentfield": null,
   "parenttype": null,
   "property": "collapsible",
   "property_type": "Check",
   "row_name": null,
   "value": "0"
  },
  {
   "_assign": null,
   "_comments": null,
   "_liked_by": null,
   "_user_tags": null,
   "creation": "2022-03-14 13:58:03.194576",
   "default_value": null,
   "doc_type": "Sales Order",
   "docstatus": 0,
   "doctype_or_field": "DocField",
   "field_name": "sec_tax_breakup",
   "idx": 0,
   "modified": "2022-03-14 13:58:03.194576",
   "modified_by": "Administrator",
   "name": "Sales Order-sec_tax_breakup-collapsible",
   "owner": "Administrator",
   "parent": null,
   "parentfield": null,
   "parenttype": null,
   "property": "collapsible",
   "property_type": "Check",
   "row_name": null,
   "value": "0"
  },
  {
   "_assign": null,
   "_comments": null,
   "_liked_by": null,
   "_user_tags": null,
   "creation": "2022-03-14 13:58:03.071184",
   "default_value": null,
   "doc_type": "Sales Order",
   "docstatus": 0,
   "doctype_or_field": "DocField",
   "field_name": "packing_list",
   "idx": 0,
   "modified": "2022-03-14 13:58:03.071184",
   "modified_by": "Administrator",
   "name": "Sales Order-packing_list-collapsible",
   "owner": "Administrator",
   "parent": null,
   "parentfield": null,
   "parenttype": null,
   "property": "collapsible",
   "property_type": "Check",
   "row_name": null,
   "value": "0"
  },
  {
   "_assign": null,
   "_comments": null,
   "_liked_by": null,
   "_user_tags": null,
   "creation": "2022-03-14 13:58:02.927924",
   "default_value": null,
   "doc_type": "Sales Order",
   "docstatus": 0,
   "doctype_or_field": "DocField",
   "field_name": "currency_and_price_list",
   "idx": 0,
   "modified": "2022-03-14 13:58:02.927924",
   "modified_by": "Administrator",
   "name": "Sales Order-currency_and_price_list-collapsible",
   "owner": "Administrator",
   "parent": null,
   "parentfield": null,
   "parenttype": null,
   "property": "collapsible",
   "property_type": "Check",
   "row_name": null,
   "value": "0"
  },
  {
   "_assign": null,
   "_comments": null,
   "_liked_by": null,
   "_user_tags": null,
   "creation": "2022-03-14 13:58:02.630833",
   "default_value": null,
   "doc_type": "Sales Order",
   "docstatus": 0,
   "doctype_or_field": "DocField",
   "field_name": "contact_info",
   "idx": 0,
   "modified": "2022-03-14 13:58:02.630833",
   "modified_by": "Administrator",
   "name": "Sales Order-contact_info-collapsible",
   "owner": "Administrator",
   "parent": null,
   "parentfield": null,
   "parenttype": null,
   "property": "collapsible",
   "property_type": "Check",
   "row_name": null,
   "value": "0"
  },
  {
   "_assign": null,
   "_comments": null,
   "_liked_by": null,
   "_user_tags": null,
   "creation": "2022-03-07 01:50:21.072355",
   "default_value": null,
   "doc_type": "Sales Order",
   "docstatus": 0,
   "doctype_or_field": "DocField",
   "field_name": "apply_discount_on",
   "idx": 0,
   "modified": "2022-03-07 01:50:21.072355",
   "modified_by": "Administrator",
   "name": "Sales Order-apply_discount_on-hidden",
   "owner": "Administrator",
   "parent": null,
   "parentfield": null,
   "parenttype": null,
   "property": "hidden",
   "property_type": "Check",
   "row_name": null,
   "value": "1"
  },
  {
   "_assign": null,
   "_comments": null,
   "_liked_by": null,
   "_user_tags": null,
   "creation": "2022-03-07 01:49:17.409944",
   "default_value": null,
   "doc_type": "Sales Order",
   "docstatus": 0,
   "doctype_or_field": "DocField",
   "field_name": "currency_and_price_list",
   "idx": 0,
   "modified": "2022-03-07 01:49:17.409944",
   "modified_by": "Administrator",
   "name": "Sales Order-currency_and_price_list-hidden",
   "owner": "Administrator",
   "parent": null,
   "parentfield": null,
   "parenttype": null,
   "property": "hidden",
   "property_type": "Check",
   "row_name": null,
   "value": "1"
  },
  {
   "_assign": null,
   "_comments": null,
   "_liked_by": null,
   "_user_tags": null,
   "creation": "2022-03-07 01:41:19.413481",
   "default_value": null,
   "doc_type": "Sales Order",
   "docstatus": 0,
   "doctype_or_field": "DocField",
   "field_name": "order_type",
   "idx": 0,
   "modified": "2022-03-07 01:41:19.413481",
   "modified_by": "Administrator",
   "name": "Sales Order-order_type-hidden",
   "owner": "Administrator",
   "parent": null,
   "parentfield": null,
   "parenttype": null,
   "property": "hidden",
   "property_type": "Check",
   "row_name": null,
   "value": "1"
  },
  {
   "_assign": null,
   "_comments": null,
   "_liked_by": null,
   "_user_tags": null,
   "creation": "2022-02-17 07:37:49.501186",
   "default_value": null,
   "doc_type": "Sales Order",
   "docstatus": 0,
   "doctype_or_field": "DocField",
   "field_name": "delivery_date",
   "idx": 0,
   "modified": "2022-02-17 07:37:49.501186",
   "modified_by": "Administrator",
   "name": "Sales Order-delivery_date-depends_on",
   "owner": "Administrator",
   "parent": null,
   "parentfield": null,
   "parenttype": null,
   "property": "depends_on",
   "property_type": "Data",
   "row_name": null,
   "value": ""
  },
  {
   "_assign": null,
   "_comments": null,
   "_liked_by": null,
   "_user_tags": null,
   "creation": "2022-02-16 17:28:01.913570",
   "default_value": null,
   "doc_type": "Sales Order",
   "docstatus": 0,
   "doctype_or_field": "DocField",
   "field_name": "section_break1",
   "idx": 0,
   "modified": "2022-02-16 17:28:01.913570",
   "modified_by": "Administrator",
   "name": "Sales Order-section_break1-collapsible",
   "owner": "Administrator",
   "parent": null,
   "parentfield": null,
   "parenttype": null,
   "property": "collapsible",
   "property_type": "Check",
   "row_name": null,
   "value": "0"
  },
  {
   "_assign": null,
   "_comments": null,
   "_liked_by": null,
   "_user_tags": null,
   "creation": "2022-02-16 17:28:01.783354",
   "default_value": null,
   "doc_type": "Sales Order",
   "docstatus": 0,
   "doctype_or_field": "DocField",
   "field_name": "billing_status",
   "idx": 0,
   "modified": "2022-02-16 17:28:01.783354",
   "modified_by": "Administrator",
   "name": "Sales Order-billing_status-hidden",
   "owner": "Administrator",
   "parent": null,
   "parentfield": null,
   "parenttype": null,
   "property": "hidden",
   "property_type": "Check",
   "row_name": null,
   "value": "0"
  },
  {
   "_assign": null,
   "_comments": null,
   "_liked_by": null,
   "_user_tags": null,
   "creation": "2022-02-16 17:28:01.653770",
   "default_value": null,
   "doc_type": "Sales Order",
   "docstatus": 0,
   "doctype_or_field": "DocField",
   "field_name": "project",
   "idx": 0,
   "modified": "2022-02-16 17:28:01.653770",
   "modified_by": "Administrator",
   "name": "Sales Order-project-hidden",
   "owner": "Administrator",
   "parent": null,
   "parentfield": null,
   "parenttype": null,
   "property": "hidden",
   "property_type": "Check",
   "row_name": null,
   "value": "1"
  },
  {
   "_assign": null,
   "_comments": null,
   "_liked_by": null,
   "_user_tags": null,
   "creation": "2022-02-16 17:28:01.506297",
   "default_value": null,
   "doc_type": "Sales Order",
   "docstatus": 0,
   "doctype_or_field": "DocField",
   "field_name": "inter_company_order_reference",
   "idx": 0,
   "modified": "2022-02-16 17:28:01.506297",
   "modified_by": "Administrator",
   "name": "Sales Order-inter_company_order_reference-hidden",
   "owner": "Administrator",
   "parent": null,
   "parentfield": null,
   "parenttype": null,
   "property": "hidden",
   "property_type": "Check",
   "row_name": null,
   "value": "1"
  },
  {
   "_assign": null,
   "_comments": null,
   "_liked_by": null,
   "_user_tags": null,
   "creation": "2022-02-16 17:28:01.374507",
   "default_value": null,
   "doc_type": "Sales Order",
   "docstatus": 0,
   "doctype_or_field": "DocField",
   "field_name": "represents_company",
   "idx": 0,
   "modified": "2022-02-16 17:28:01.374507",
   "modified_by": "Administrator",
   "name": "Sales Order-represents_company-hidden",
   "owner": "Administrator",
   "parent": null,
   "parentfield": null,
   "parenttype": null,
   "property": "hidden",
   "property_type": "Check",
   "row_name": null,
   "value": "1"
  },
  {
   "_assign": null,
   "_comments": null,
   "_liked_by": null,
   "_user_tags": null,
   "creation": "2022-02-16 17:28:01.244192",
   "default_value": null,
   "doc_type": "Sales Order",
   "docstatus": 0,
   "doctype_or_field": "DocField",
   "field_name": "is_internal_customer",
   "idx": 0,
   "modified": "2022-02-16 17:28:01.244192",
   "modified_by": "Administrator",
   "name": "Sales Order-is_internal_customer-hidden",
   "owner": "Administrator",
   "parent": null,
   "parentfield": null,
   "parenttype": null,
   "property": "hidden",
   "property_type": "Check",
   "row_name": null,
   "value": "1"
  },
  {
   "_assign": null,
   "_comments": null,
   "_liked_by": null,
   "_user_tags": null,
   "creation": "2022-02-16 17:28:01.046015",
   "default_value": null,
   "doc_type": "Sales Order",
   "docstatus": 0,
   "doctype_or_field": "DocField",
   "field_name": "more_info",
   "idx": 0,
   "modified": "2022-02-16 17:28:01.046015",
   "modified_by": "Administrator",
   "name": "Sales Order-more_info-collapsible",
   "owner": "Administrator",
   "parent": null,
   "parentfield": null,
   "parenttype": null,
   "property": "collapsible",
   "property_type": "Check",
   "row_name": null,
   "value": "0"
  },
  {
   "_assign": null,
   "_comments": null,
   "_liked_by": null,
   "_user_tags": null,
   "creation": "2022-02-16 17:18:20.550497",
   "default_value": null,
   "doc_type": "Sales Order",
   "docstatus": 0,
   "doctype_or_field": "DocField",
   "field_name": "loyalty_amount",
   "idx": 0,
   "modified": "2022-02-16 17:18:20.550497",
   "modified_by": "Administrator",
   "name": "Sales Order-loyalty_amount-hidden",
   "owner": "Administrator",
   "parent": null,
   "parentfield": null,
   "parenttype": null,
   "property": "hidden",
   "property_type": "Check",
   "row_name": null,
   "value": "0"
  },
  {
   "_assign": null,
   "_comments": null,
   "_liked_by": null,
   "_user_tags": null,
   "creation": "2022-02-16 17:18:20.414112",
   "default_value": null,
   "doc_type": "Sales Order",
   "docstatus": 0,
   "doctype_or_field": "DocField",
   "field_name": "loyalty_points",
   "idx": 0,
   "modified": "2022-02-16 17:18:20.414112",
   "modified_by": "Administrator",
   "name": "Sales Order-loyalty_points-hidden",
   "owner": "Administrator",
   "parent": null,
   "parentfield": null,
   "parenttype": null,
   "property": "hidden",
   "property_type": "Check",
   "row_name": null,
   "value": "0"
  },
  {
   "_assign": null,
   "_comments": null,
   "_liked_by": null,
   "_user_tags": null,
   "creation": "2022-02-16 17:14:43.064857",
   "default_value": null,
   "doc_type": "Sales Order",
   "docstatus": 0,
   "doctype_or_field": "DocField",
   "field_name": "tax_category",
   "idx": 0,
   "modified": "2022-02-16 17:14:43.064857",
   "modified_by": "Administrator",
   "name": "Sales Order-tax_category-fetch_from",
   "owner": "Administrator",
   "parent": null,
   "parentfield": null,
   "parenttype": null,
   "property": "fetch_from",
   "property_type": "Small Text",
   "row_name": null,
   "value": "customer.tax_category"
  },
  {
   "_assign": null,
   "_comments": null,
   "_liked_by": null,
   "_user_tags": null,
   "creation": "2022-02-16 17:12:01.545705",
   "default_value": null,
   "doc_type": "Sales Order",
   "docstatus": 0,
   "doctype_or_field": "DocField",
   "field_name": "column_break_33a",
   "idx": 0,
   "modified": "2022-02-16 17:12:01.545705",
   "modified_by": "Administrator",
   "name": "Sales Order-column_break_33a-hidden",
   "owner": "Administrator",
   "parent": null,
   "parentfield": null,
   "parenttype": null,
   "property": "hidden",
   "property_type": "Check",
   "row_name": null,
   "value": "1"
  },
  {
   "_assign": null,
   "_comments": null,
   "_liked_by": null,
   "_user_tags": null,
   "creation": "2022-02-16 17:10:52.358009",
   "default_value": null,
   "doc_type": "Sales Order",
   "docstatus": 0,
   "doctype_or_field": "DocField",
   "field_name": "customer_group",
   "idx": 0,
   "modified": "2022-02-16 17:10:52.358009",
   "modified_by": "Administrator",
   "name": "Sales Order-customer_group-hidden",
   "owner": "Administrator",
   "parent": null,
   "parentfield": null,
   "parenttype": null,
   "property": "hidden",
   "property_type": "Check",
   "row_name": null,
   "value": "0"
  },
  {
   "_assign": null,
   "_comments": null,
   "_liked_by": null,
   "_user_tags": null,
   "creation": "2022-02-16 17:10:52.151524",
   "default_value": null,
   "doc_type": "Sales Order",
   "docstatus": 0,
   "doctype_or_field": "DocField",
   "field_name": "contact_email",
   "idx": 0,
   "modified": "2022-02-16 17:10:52.151524",
   "modified_by": "Administrator",
   "name": "Sales Order-contact_email-hidden",
   "owner": "Administrator",
   "parent": null,
   "parentfield": null,
   "parenttype": null,
   "property": "hidden",
   "property_type": "Check",
   "row_name": null,
   "value": "0"
  },
  {
   "_assign": null,
   "_comments": null,
   "_liked_by": null,
   "_user_tags": null,
   "creation": "2022-02-16 17:05:59.744731",
   "default_value": null,
   "doc_type": "Sales Order",
   "docstatus": 0,
   "doctype_or_field": "DocField",
   "field_name": "amended_from",
   "idx": 0,
   "modified": "2022-02-16 17:05:59.744731",
   "modified_by": "Administrator",
   "name": "Sales Order-amended_from-hidden",
   "owner": "Administrator",
   "parent": null,
   "parentfield": null,
   "parenttype": null,
   "property": "hidden",
   "property_type": "Check",
   "row_name": null,
   "value": "0"
  },
  {
   "_assign": null,
   "_comments": null,
   "_liked_by": null,
   "_user_tags": null,
   "creation": "2022-01-25 12:25:11.303373",
   "default_value": null,
   "doc_type": "Sales Order",
   "docstatus": 0,
   "doctype_or_field": "DocField",
   "field_name": "printing_details",
   "idx": 0,
   "modified": "2022-01-25 12:25:11.303373",
   "modified_by": "Administrator",
   "name": "Sales Order-printing_details-hidden",
   "owner": "Administrator",
   "parent": null,
   "parentfield": null,
   "parenttype": null,
   "property": "hidden",
   "property_type": "Check",
   "row_name": null,
   "value": "1"
  },
  {
   "_assign": null,
   "_comments": null,
   "_liked_by": null,
   "_user_tags": null,
   "creation": "2022-01-25 11:56:46.228663",
   "default_value": null,
   "doc_type": "Sales Order",
   "docstatus": 0,
   "doctype_or_field": "DocField",
   "field_name": "totals",
   "idx": 0,
   "modified": "2022-01-25 11:56:46.228663",
   "modified_by": "Administrator",
   "name": "Sales Order-totals-label",
   "owner": "Administrator",
   "parent": null,
   "parentfield": null,
   "parenttype": null,
   "property": "label",
   "property_type": "Data",
   "row_name": null,
   "value": "Total Amount"
  },
  {
   "_assign": null,
   "_comments": null,
   "_liked_by": null,
   "_user_tags": null,
   "creation": "2022-01-25 11:48:36.617316",
   "default_value": null,
   "doc_type": "Sales Order",
   "docstatus": 0,
   "doctype_or_field": "DocField",
   "field_name": "apply_discount_on",
   "idx": 0,
   "modified": "2022-01-25 11:48:36.617316",
   "modified_by": "Administrator",
   "name": "Sales Order-apply_discount_on-default",
   "owner": "Administrator",
   "parent": null,
   "parentfield": null,
   "parenttype": null,
   "property": "default",
   "property_type": "Text",
   "row_name": null,
   "value": "Net Total"
  },
  {
   "_assign": null,
   "_comments": null,
   "_liked_by": null,
   "_user_tags": null,
   "creation": "2022-01-25 11:48:36.239939",
   "default_value": null,
   "doc_type": "Sales Order",
   "docstatus": 0,
   "doctype_or_field": "DocField",
   "field_name": "apply_discount_on",
   "idx": 0,
   "modified": "2022-01-25 11:48:36.239939",
   "modified_by": "Administrator",
   "name": "Sales Order-apply_discount_on-options",
   "owner": "Administrator",
   "parent": null,
   "parentfield": null,
   "parenttype": null,
   "property": "options",
   "property_type": "Text",
   "row_name": null,
   "value": "Net Total\nGrand Total\n"
  },
  {
   "_assign": null,
   "_comments": null,
   "_liked_by": null,
   "_user_tags": null,
   "creation": "2022-01-25 11:34:39.277402",
   "default_value": null,
   "doc_type": "Sales Order",
   "docstatus": 0,
   "doctype_or_field": "DocField",
   "field_name": "contact_info",
   "idx": 0,
   "modified": "2022-01-25 11:34:39.277402",
   "modified_by": "Administrator",
   "name": "Sales Order-contact_info-hidden",
   "owner": "Administrator",
   "parent": null,
   "parentfield": null,
   "parenttype": null,
   "property": "hidden",
   "property_type": "Check",
   "row_name": null,
   "value": "1"
  },
  {
   "_assign": null,
   "_comments": null,
   "_liked_by": null,
   "_user_tags": null,
   "creation": "2022-01-25 11:27:14.537397",
   "default_value": null,
   "doc_type": "Sales Order",
   "docstatus": 0,
   "doctype_or_field": "DocField",
   "field_name": "delivery_date",
   "idx": 0,
   "modified": "2022-01-25 11:27:14.537397",
   "modified_by": "Administrator",
   "name": "Sales Order-delivery_date-mandatory_depends_on",
   "owner": "Administrator",
   "parent": null,
   "parentfield": null,
   "parenttype": null,
   "property": "mandatory_depends_on",
   "property_type": "Data",
   "row_name": null,
   "value": "eval:doc.naming_series != \"WKS-PI-.MM.YY.-\""
  },
  {
   "_assign": null,
   "_comments": null,
   "_liked_by": null,
   "_user_tags": null,
   "creation": "2022-01-25 09:54:39.935929",
   "default_value": null,
   "doc_type": "Sales Order",
   "docstatus": 0,
   "doctype_or_field": "DocField",
   "field_name": "order_type",
   "idx": 0,
   "modified": "2022-01-25 09:54:39.935929",
   "modified_by": "Administrator",
   "name": "Sales Order-order_type-depends_on",
   "owner": "Administrator",
   "parent": null,
   "parentfield": null,
   "parenttype": null,
   "property": "depends_on",
   "property_type": "Data",
   "row_name": null,
   "value": "eval:doc.naming_series != \"WKS-PI-.MM.YY.-\""
  },
  {
   "_assign": null,
   "_comments": null,
   "_liked_by": null,
   "_user_tags": null,
   "creation": "2022-01-25 09:49:37.238721",
   "default_value": null,
   "doc_type": "Sales Order",
   "docstatus": 0,
   "doctype_or_field": "DocField",
   "field_name": "order_type",
   "idx": 0,
   "modified": "2022-01-25 09:49:37.238721",
   "modified_by": "Administrator",
   "name": "Sales Order-order_type-options",
   "owner": "Administrator",
   "parent": null,
   "parentfield": null,
   "parenttype": null,
   "property": "options",
   "property_type": "Text",
   "row_name": null,
   "value": "Sales\n"
  },
  {
   "_assign": null,
   "_comments": null,
   "_liked_by": null,
   "_user_tags": null,
   "creation": "2022-01-16 14:06:11.494820",
   "default_value": null,
   "doc_type": "Sales Order",
   "docstatus": 0,
   "doctype_or_field": "DocField",
   "field_name": "scan_barcode",
   "idx": 0,
   "modified": "2022-01-16 14:06:11.494820",
   "modified_by": "Administrator",
   "name": "Sales Order-scan_barcode-hidden",
   "owner": "Administrator",
   "parent": null,
   "parentfield": null,
   "parenttype": null,
   "property": "hidden",
   "property_type": "Check",
   "row_name": null,
   "value": "1"
  },
  {
   "_assign": null,
   "_comments": null,
   "_liked_by": null,
   "_user_tags": null,
   "creation": "2022-01-11 09:05:56.164976",
   "default_value": null,
   "doc_type": "Sales Order",
   "docstatus": 0,
   "doctype_or_field": "DocField",
   "field_name": "column_break_50",
   "idx": 0,
   "modified": "2022-01-11 09:05:56.164976",
   "modified_by": "Administrator",
   "name": "Sales Order-column_break_50-hidden",
   "owner": "Administrator",
   "parent": null,
   "parentfield": null,
   "parenttype": null,
   "property": "hidden",
   "property_type": "Check",
   "row_name": null,
   "value": "1"
  },
  {
   "_assign": null,
   "_comments": null,
   "_liked_by": null,
   "_user_tags": null,
   "creation": "2022-01-11 09:03:04.113624",
   "default_value": null,
   "doc_type": "Sales Order",
   "docstatus": 0,
   "doctype_or_field": "DocField",
   "field_name": "base_total_taxes_and_charges",
   "idx": 0,
   "modified": "2022-01-11 09:03:04.113624",
   "modified_by": "Administrator",
   "name": "Sales Order-base_total_taxes_and_charges-in_list_view",
   "owner": "Administrator",
   "parent": null,
   "parentfield": null,
   "parenttype": null,
   "property": "in_list_view",
   "property_type": "Check",
   "row_name": null,
   "value": "1"
  },
  {
   "_assign": null,
   "_comments": null,
   "_liked_by": null,
   "_user_tags": null,
   "creation": "2022-01-11 09:01:57.123851",
   "default_value": null,
   "doc_type": "Sales Order",
   "docstatus": 0,
   "doctype_or_field": "DocField",
   "field_name": "column_break3",
   "idx": 0,
   "modified": "2022-01-11 09:01:57.123851",
   "modified_by": "Administrator",
   "name": "Sales Order-column_break3-hidden",
   "owner": "Administrator",
   "parent": null,
   "parentfield": null,
   "parenttype": null,
   "property": "hidden",
   "property_type": "Check",
   "row_name": null,
   "value": "1"
  },
  {
   "_assign": null,
   "_comments": null,
   "_liked_by": null,
   "_user_tags": null,
   "creation": "2022-01-04 12:10:52.030410",
   "default_value": null,
   "doc_type": "Sales Order",
   "docstatus": 0,
   "doctype_or_field": "DocField",
   "field_name": "subscription_section",
   "idx": 0,
   "modified": "2022-01-04 12:10:52.030410",
   "modified_by": "Administrator",
   "name": "Sales Order-subscription_section-hidden",
   "owner": "Administrator",
   "parent": null,
   "parentfield": null,
   "parenttype": null,
   "property": "hidden",
   "property_type": "Check",
   "row_name": null,
   "value": "1"
  },
  {
   "_assign": null,
   "_comments": null,
   "_liked_by": null,
   "_user_tags": null,
   "creation": "2022-01-04 11:32:57.438464",
   "default_value": null,
   "doc_type": "Sales Order",
   "docstatus": 0,
   "doctype_or_field": "DocField",
   "field_name": "shipping_rule",
   "idx": 0,
   "modified": "2022-01-04 11:32:57.438464",
   "modified_by": "Administrator",
   "name": "Sales Order-shipping_rule-hidden",
   "owner": "Administrator",
   "parent": null,
   "parentfield": null,
   "parenttype": null,
   "property": "hidden",
   "property_type": "Check",
   "row_name": null,
   "value": "1"
  },
  {
   "_assign": null,
   "_comments": null,
   "_liked_by": null,
   "_user_tags": null,
   "creation": "2021-12-16 12:50:45.362685",
   "default_value": null,
   "doc_type": "Sales Order",
   "docstatus": 0,
   "doctype_or_field": "DocField",
   "field_name": "in_words",
   "idx": 0,
   "modified": "2021-12-16 12:50:45.362685",
   "modified_by": "Administrator",
   "name": "Sales Order-in_words-print_hide",
   "owner": "Administrator",
   "parent": null,
   "parentfield": null,
   "parenttype": null,
   "property": "print_hide",
   "property_type": "Check",
   "row_name": null,
   "value": "0"
  },
  {
   "_assign": null,
   "_comments": null,
   "_liked_by": null,
   "_user_tags": null,
   "creation": "2021-12-16 12:50:45.334696",
   "default_value": null,
   "doc_type": "Sales Order",
   "docstatus": 0,
   "doctype_or_field": "DocField",
   "field_name": "in_words",
   "idx": 0,
   "modified": "2021-12-16 12:50:45.334696",
   "modified_by": "Administrator",
   "name": "Sales Order-in_words-hidden",
   "owner": "Administrator",
   "parent": null,
   "parentfield": null,
   "parenttype": null,
   "property": "hidden",
   "property_type": "Check",
   "row_name": null,
   "value": "0"
  },
  {
   "_assign": null,
   "_comments": null,
   "_liked_by": null,
   "_user_tags": null,
   "creation": "2021-12-16 12:50:44.538117",
   "default_value": null,
   "doc_type": "Sales Order",
   "docstatus": 0,
   "doctype_or_field": "DocField",
   "field_name": "disable_rounded_total",
   "idx": 0,
   "modified": "2021-12-16 12:50:44.538117",
   "modified_by": "Administrator",
   "name": "Sales Order-disable_rounded_total-default",
   "owner": "Administrator",
   "parent": null,
   "parentfield": null,
   "parenttype": null,
   "property": "default",
   "property_type": "Text",
   "row_name": null,
   "value": "0"
  },
  {
   "_assign": null,
   "_comments": null,
   "_liked_by": null,
   "_user_tags": null,
   "creation": "2021-12-16 12:50:44.515072",
   "default_value": null,
   "doc_type": "Sales Order",
   "docstatus": 0,
   "doctype_or_field": "DocField",
   "field_name": "rounded_total",
   "idx": 0,
   "modified": "2021-12-16 12:50:44.515072",
   "modified_by": "Administrator",
   "name": "Sales Order-rounded_total-print_hide",
   "owner": "Administrator",
   "parent": null,
   "parentfield": null,
   "parenttype": null,
   "property": "print_hide",
   "property_type": "Check",
   "row_name": null,
   "value": "0"
  },
  {
   "_assign": null,
   "_comments": null,
   "_liked_by": null,
   "_user_tags": null,
   "creation": "2021-12-16 12:50:44.492811",
   "default_value": null,
   "doc_type": "Sales Order",
   "docstatus": 0,
   "doctype_or_field": "DocField",
   "field_name": "rounded_total",
   "idx": 0,
   "modified": "2021-12-16 12:50:44.492811",
   "modified_by": "Administrator",
   "name": "Sales Order-rounded_total-hidden",
   "owner": "Administrator",
   "parent": null,
   "parentfield": null,
   "parenttype": null,
   "property": "hidden",
   "property_type": "Check",
   "row_name": null,
   "value": "0"
  },
  {
   "_assign": null,
   "_comments": null,
   "_liked_by": null,
   "_user_tags": null,
   "creation": "2021-12-16 12:50:44.470139",
   "default_value": null,
   "doc_type": "Sales Order",
   "docstatus": 0,
   "doctype_or_field": "DocField",
   "field_name": "base_rounded_total",
   "idx": 0,
   "modified": "2021-12-16 12:50:44.470139",
   "modified_by": "Administrator",
   "name": "Sales Order-base_rounded_total-print_hide",
   "owner": "Administrator",
   "parent": null,
   "parentfield": null,
   "parenttype": null,
   "property": "print_hide",
   "property_type": "Check",
   "row_name": null,
   "value": "1"
  },
  {
   "_assign": null,
   "_comments": null,
   "_liked_by": null,
   "_user_tags": null,
   "creation": "2021-12-16 12:50:44.447134",
   "default_value": null,
   "doc_type": "Sales Order",
   "docstatus": 0,
   "doctype_or_field": "DocField",
   "field_name": "base_rounded_total",
   "idx": 0,
   "modified": "2021-12-16 12:50:44.447134",
   "modified_by": "Administrator",
   "name": "Sales Order-base_rounded_total-hidden",
   "owner": "Administrator",
   "parent": null,
   "parentfield": null,
   "parenttype": null,
   "property": "hidden",
   "property_type": "Check",
   "row_name": null,
   "value": "0"
  },
  {
   "_assign": null,
   "_comments": null,
   "_liked_by": null,
   "_user_tags": null,
   "creation": "2021-12-16 12:50:43.644656",
   "default_value": null,
   "doc_type": "Sales Order",
   "docstatus": 0,
   "doctype_or_field": "DocField",
   "field_name": "tax_id",
   "idx": 0,
   "modified": "2021-12-16 12:50:43.644656",
   "modified_by": "Administrator",
   "name": "Sales Order-tax_id-print_hide",
   "owner": "Administrator",
   "parent": null,
   "parentfield": null,
   "parenttype": null,
   "property": "print_hide",
   "property_type": "Check",
   "row_name": null,
   "value": "0"
  },
  {
   "_assign": null,
   "_comments": null,
   "_liked_by": null,
   "_user_tags": null,
   "creation": "2021-12-16 12:50:43.622111",
   "default_value": null,
   "doc_type": "Sales Order",
   "docstatus": 0,
   "doctype_or_field": "DocField",
   "field_name": "tax_id",
   "idx": 0,
   "modified": "2021-12-16 12:50:43.622111",
   "modified_by": "Administrator",
   "name": "Sales Order-tax_id-hidden",
   "owner": "Administrator",
   "parent": null,
   "parentfield": null,
   "parenttype": null,
   "property": "hidden",
   "property_type": "Check",
   "row_name": null,
   "value": "0"
  },
  {
   "_assign": null,
   "_comments": null,
   "_liked_by": null,
   "_user_tags": null,
   "creation": "2021-12-16 11:38:21.060895",
   "default_value": null,
   "doc_type": "Sales Order",
   "docstatus": 0,
   "doctype_or_field": "DocField",
   "field_name": "payment_schedule",
   "idx": 0,
   "modified": "2021-12-16 11:38:21.060895",
   "modified_by": "Administrator",
   "name": "Sales Order-payment_schedule-print_hide",
   "owner": "Administrator",
   "parent": null,
   "parentfield": null,
   "parenttype": null,
   "property": "print_hide",
   "property_type": "Check",
   "row_name": null,
   "value": "1"
  },
  {
   "_assign": null,
   "_comments": null,
   "_liked_by": null,
   "_user_tags": null,
   "creation": "2021-12-16 11:38:21.023598",
   "default_value": null,
   "doc_type": "Sales Order",
   "docstatus": 0,
   "doctype_or_field": "DocField",
   "field_name": "due_date",
   "idx": 0,
   "modified": "2021-12-16 11:38:21.023598",
   "modified_by": "Administrator",
   "name": "Sales Order-due_date-print_hide",
   "owner": "Administrator",
   "parent": null,
   "parentfield": null,
   "parenttype": null,
   "property": "print_hide",
   "property_type": "Check",
   "row_name": null,
   "value": "0"
  }
 ],
 "sync_on_migrate": 1
}