{
 "chart_name": "Unit Wise Delivery",
 "chart_type": "Report",
 "creation": "2023-07-18 12:53:33.451670",
 "custom_options": "{\"type\": \"bar\", \"axisOptions\": {\"shortenYAxisNumbers\": 1}, \"height\": 280}",
 "docstatus": 0,
 "doctype": "Dashboard Chart",
 "filters_json": "{\"from_date\":\"2023-07-01\",\"to_date\":\"2023-07-31\",\"item_group\":[\"Raw Material\",\"Pavers\",\"Compound Walls\"]}",
 "group_by_type": "Count",
 "idx": 0,
 "is_public": 0,
 "is_standard": 1,
 "modified": "2023-07-18 12:53:33.568100",
 "modified_by": "Administrator",
 "module": "Ganapathy Pavers",
 "name": "Unit Wise Delivery",
 "number_of_groups": 0,
 "owner": "Administrator",
 "report_name": "Unit Wise Delivery",
 "time_interval": "Yearly",
 "timeseries": 0,
 "timespan": "Last Year",
 "type": "Bar",
 "use_report_chart": 1,
 "y_axis": []
}