{
 "absolute_value": 0,
 "align_labels_right": 0,
 "creation": "2022-04-15 11:37:49.497837",
 "css": ".master{\n    font-size:12px;\n}\n\n.master td{\n    font-size:12px;\n}\n\n.master th{\n    font-size:12px;\n}\n",
 "custom_format": 1,
 "default_print_language": "en-US",
 "disabled": 0,
 "doc_type": "Quotation",
 "docstatus": 0,
 "doctype": "Print Format",
 "font": "Default",
 "html": "<div class=\"master\">\n{% if letter_head and not no_letterhead -%}\n{% if print_settings.repeat_header_footer %}\n<div class=\"letter-head\">{{ letter_head }}</div>\n{%- endif %}\n{%- endif %}\n<hr style=\"width;100%; border-bottom: 1px solid grey;\">\n<div class=\"master\" style=\"border: 1px solid grey;\">\n    <div style=\"width;100%; border-bottom: 1px solid grey; background-color: orange; font-size:20px; color:black; height:40px; border-top:5px solid orange\" align=\"center\"><b>QUOTATION</b></div>\n    <div>\n        <table  width=\"100%\" style=\"color:black; font-size:15px;\">\n            <tr>\n                <td width=\"13%\"><b>To</b></td>\n                <td>:</td>\n                <td><b>{{ doc.party_name or \"\" }}</b><br><br>\n                    {{ doc.address_display or \"\" }}</td>\n                    <td width=\"5%\"></td>\n                    <td width=\"5%\"></td>\n                <td width=\"20%\" ><b>Quotation :<br>No.</b><br><br>\n                <b>Date&nbsp;&nbsp;&nbsp;&nbsp;&nbsp;&nbsp;&nbsp;&nbsp;&nbsp;&nbsp;:</b>\n                </td>\n                <td width=\"20%\">{{ doc.name }}<br><br>\n                    {{  doc.get_formatted(\"transaction_date\") or \"\" }}\n                </td>\n            </tr>\n        </table>\n        <div style=\"font-size:15px; color:black; padding:5px\">\n            <table style=\"color:black\">\n            <tr>\n                <td align=\"left\" width=\"20%\"><b>Kind Attn</b><br></td>\n                <td align=\"left\">: </td>\n            </tr>\n            <tr>\n                <td align=\"left\" width=\"20%\"><b>Sub</b></td>\n                <td align=\"left\">: Rate Quotation For Paver Blocks.</td>\n            </tr>\n            </table>\n            <table style=\"color:black\">\n            <tr>\n                <td><b>Sir / Madam,</b><br></td>\n                <td></td>\n            </tr>\n            <tr>\n                <td>&nbsp; Thank you very much for your enquiry, We have great pleasure to submitting for our least quotations.</td>\n                <td></td>\n            </tr>\n            </table>\n        </div>\n    </div>\n    <div style=\"padding:5px;\">\n        {% set serial_no=[] %}\n        <table style=\"border:1px solid grey; color:black;\">\n            {% set tablelength=10 %}\n            <tr style=\"border-bottom:1px solid grey\">\n                <td style=\"background-color:orange !important;\"><b>S.No.</b></td>\n                <td style=\"border-left:1px solid grey;background-color:orange !important;\" align=\"center\"><b>Particulars</b></td>\n                <td style=\"border-left:1px solid grey;background-color:orange !important;\" align=\"center\"><b>Qty</b></td>\n                <td style=\"border-left:1px solid grey;background-color:orange  !important;\" align=\"center\"><b>Uom</b></td>\n                <td style=\"border-left:1px solid grey;background-color:orange  !important;\" align=\"center\"><b>Rate</b></td>\n                <td style=\"border-left:1px solid grey;background-color:orange  !important;\" align=\"center\"><b>Amount</b></td>\n            </tr>\n            <!--for loop for items-->\n            \n            {% for item in doc.items %}\n                {% set _=serial_no.append(1) %}\n            <tr>\n                <td align=\"left\" width=\"6%\">{{ serial_no|length }}</td>\n                <td align=\"left\" style=\"border-left:1px solid grey;\" width=\"36%\">{{ item.item_name or \"\" }}</td>\n                <td align=\"right\" style=\"border-left:1px solid grey;\" width=\"10%\">{{ item.qty or \"\" }}</td>\n                <td align=\"right\" style=\"border-left:1px solid grey;\" width=\"6%\">{{ item.uom or \"\" }}</td>\n                <td align=\"right\" style=\"border-left:1px solid grey;\" width=\"15%\">{{ \"%.2f\"|format(item.rate) or \"\" }}</td>\n                <td align=\"right\" style=\"border-left:1px solid grey;\" width=\"15%\">{{ \"%.2f\"|format(item.amount) or \"\" }}</td>\n            </tr>\n            {% endfor %}\n            \n             </table>\n            </div>\n            <div class=\"secondhalf\" width=\"100%\">\n            <table align=\"right\" style=\"color:black\" width=\"100%\">\n            <tr align=\"right\">\n                <td width=\"20%\"></td>\n                <td width=\"20%\"></td>\n                <td width=\"20%\"></td>\n                <td width=\"20%\"><b>GST :</b></td>\n                <td width=\"20%\" align=\"right\">{{ \"%.2f\"|format(doc.total_taxes_and_charges) or \"\" }}</td>\n            </tr>\n            <tr align=\"right\" >\n                <td width=\"20%\"></td>\n                <td width=\"20%\"></td>\n                <td width=\"20%\"></td>\n                <td width=\"20%\"><b>Grand Total :</b></td>\n                <td width=\"20%\" align=\"right\">{{ \"%.2f\"|format(doc.grand_total) or \"\" }}</td>\n            </tr>\n        </table>\n    </div>\n    <div width=\"100%\" style=\"color:black;padding:5px;\">\n        <p width=\"100%\"><b>Terms & Conditions</b><br>\n        {{doc.terms or \" \"}}<br>\n        </p>\n    </div>\n    <div style=\"padding:5px;\">\n        <table width=100% style=\"color:black; border:1px solid grey; border-top:0px;\">\n            {% set bank = frappe.get_doc(\"Bank Account\", \"Sri Ganapathy Fly Ash Bricks - Bank of India\")%}\n            <tr>\n                <td align=\"right\" style=\"width:50%; color:black; background-color:orange; font-size:15px; border: 1px solid grey; border-right: 0px;\"><b>Bank</b></td>\n                <td align=\"left\" style=\"width:50%; color:black; background-color:orange; font-size:15px; border: 1px solid grey; border-left: 0px;\"><b>Details</b></td>\n            </tr>\n            \n            <tr>\n                <td><b>Name : <span style=\"color:blue\">{{bank.account_name or \"\" }}</span></b></td>\n                <td><b>Branch : <span style=\"color:blue\">Ganapathypalayam</span></b></td>\n            </tr>\n            <tr>\n                <td><b>A/C No : <span style=\"color:blue\">{{bank.bank_account_no or \"\" }}</span></b></td>\n                <td><b>IFSC : <span style=\"color:blue\">{{bank.branch_code or \"\" }}</span></b></td>\n            </tr>\n            <tr>\n                <td><b>Bank : <span style=\"color:blue\">{{bank.bank or \"\" }}</span></b></td>\n                <td></td>\n            </tr>\n        </table>\n    </div>\n</div>\n\n</div>",
 "idx": 0,
 "line_breaks": 0,
 "modified": "2022-06-16 16:28:46.171399",
 "modified_by": "Administrator",
 "module": "Ganapathy Pavers",
 "name": "Quotation",
 "owner": "Administrator",
 "print_format_builder": 0,
 "print_format_type": "Jinja",
 "raw_printing": 0,
 "show_section_headings": 0,
 "standard": "Yes"
}